hello_aaingyunii-0.2.0.dist-info/METADATA
hello_aaingyunii-0.2.0.dist-info/WHEEL
hello_aaingyunii/__init__.py
hello_aaingyunii-0.2.0.dist-info/RECORD
