Metadata-Version: 2.1
Name: hello_aaingyunii
Version: 0.2.0
Summary: The python program I'm distributing for the first time
Author-Email: aaingyunii <dlsrbs98@gmail.com>
License: MIT
Requires-Python: >=3.8
